pyeasythymio/__init__.py
pyeasythymio/easythymio.py
pyeasythymio/sm.py
pyeasythymio-0.2.0.dist-info/METADATA
pyeasythymio-0.2.0.dist-info/WHEEL
pyeasythymio-0.2.0.dist-info/licenses/LICENSE
pyeasythymio-0.2.0.dist-info/RECORD
