Metadata-Version: 2.4
Name: pyeasythymio
Version: 0.2.0
Summary: A small package to allow Thymio to be coded using Python in sequential manner.
Project-URL: Homepage, https://github.com/kurniawano/pyeasythymio
Project-URL: Issues, https://github.com/kurniawano/pyeasythymio/issues
Author-email: Oka Kurniawan <oka_kurniawan@sutd.edu.sg>
License-Expression: MIT
License-File: LICENSE
Classifier: Operating System :: OS Independent
Classifier: Programming Language :: Python :: 3
Requires-Python: >=3.12
Requires-Dist: tdmclient
